pyorm/__init__.py
pyorm/utils/__init__.py
pyorm/utils/pdo/__init__.py
pyorm/utils/pdo/exception.py
pyorm/utils/pdo/pdo.py
pyorm/utils/pdo/databases/__init__.py
pyorm/utils/pdo/databases/mysql_database.py
pyorm/utils/pdo/databases/postgresql_database.py
pyorm/utils/pdo/databases/sqlite_database.py
pyorm_pip-1.0.0.dist-info/METADATA
pyorm_pip-1.0.0.dist-info/WHEEL
pyorm_pip-1.0.0.dist-info/top_level.txt
pyorm_pip-1.0.0.dist-info/RECORD
